text2phonemefast/__init__.py
text2phonemefast/language_phoneme_limits.py
text2phonemefast/text2phonemefast.py
text2phonemefast-0.2.1.dist-info/licenses/LICENSE.txt
text2phonemefast-0.2.1.dist-info/METADATA
text2phonemefast-0.2.1.dist-info/WHEEL
text2phonemefast-0.2.1.dist-info/top_level.txt
text2phonemefast-0.2.1.dist-info/RECORD
