Metadata-Version: 2.4
Name: text2phonemefast
Version: 0.2.1
Summary: A Python Library to convert text to phoneme sequence fast - used for XPhoneBERT (Forked and enhanced from original work by Linh The Nguyen)
Home-page: https://github.com/manhcuong02/Text2PhonemeFast
Author: Nguyễn Mạnh Cường
Author-email: Nguyễn Mạnh Cường <manhcuong17072002@gmail.com>
Maintainer: Nguyễn Mạnh Cường
Maintainer-email: Nguyễn Mạnh Cường <manhcuong17072002@gmail.com>
License:                                  Apache License
Project-URL: Homepage, https://github.com/manhcuong02/Text2PhonemeFast
Project-URL: Bug Tracker, https://github.com/manhcuong02/Text2PhonemeFast/issues
Keywords: text2phonemefast
Classifier: Development Status :: 4 - Beta
Classifier: Intended Audience :: Developers
Classifier: License :: OSI Approved :: Apache Software License
Classifier: Programming Language :: Python :: 3
Requires-Python: >=3.10
License-File: LICENSE.txt
Requires-Dist: transformers==4.51.3
Requires-Dist: tqdm==4.67.1
Requires-Dist: segments==2.3.0
Requires-Dist: unidecode==1.4.0
Requires-Dist: torch==2.6.0
Dynamic: author
Dynamic: home-page
Dynamic: license-file
Dynamic: maintainer
Dynamic: requires-python
